pdbfairy/__init__.py
pdbfairy/commands/__init__.py
pdbfairy/commands/compare_interactions.py
pdbfairy/commands/find_interactions.py
pdbfairy/gen_test.py
pdbfairy/main.py
pdbfairy/utils.py
pdbfairy-1.0.0.dist-info/entry_points.txt
pdbfairy-1.0.0.dist-info/LICENSE
pdbfairy-1.0.0.dist-info/WHEEL
pdbfairy-1.0.0.dist-info/METADATA
pdbfairy-1.0.0.dist-info/RECORD
