Metadata-Version: 2.1
Name: pdbfairy
Version: 1.0.0
Summary: 
Author: Danny Roberts
Requires-Python: >=3.8,<4.0
Classifier: Programming Language :: Python :: 3
Classifier: Programming Language :: Python :: 3.10
Classifier: Programming Language :: Python :: 3.8
Classifier: Programming Language :: Python :: 3.9
Requires-Dist: biopython (>=1.74,<2.0)
Requires-Dist: click (>=7.0,<8.0)
Requires-Dist: dimagi-memoized (>=1.1.3,<2.0.0)
Requires-Dist: numpy (>=1.23,<1.24)
